<?xml version="1.0" encoding="UTF-8"?>
<objects serializationModel="Studio.02.02.00">
	<object class="AudioFile" id="{6990f127-da78-40a7-8b26-61d8482c2b18}">
		<property name="assetPath">
			<value>Level 2 Door Open.wav</value>
		</property>
		<property name="frequencyInKHz">
			<value>48</value>
		</property>
		<property name="channelCount">
			<value>2</value>
		</property>
		<property name="length">
			<value>3.1638333333333333</value>
		</property>
		<relationship name="masterAssetFolder">
			<destination>{6304bdae-f9da-451c-a56a-f12994e40e9e}</destination>
		</relationship>
	</object>
</objects>
